timedotc/_init__.py
timedotc/timedotc.py
timedotc-0.1.0.dist-info/LICENSE
timedotc-0.1.0.dist-info/METADATA
timedotc-0.1.0.dist-info/WHEEL
timedotc-0.1.0.dist-info/top_level.txt
timedotc-0.1.0.dist-info/RECORD
